odoo/addons/sale_order_mitxelena/__init__.py
odoo/addons/sale_order_mitxelena/__manifest__.py
odoo/addons/sale_order_mitxelena/controllers/__init__.py
odoo/addons/sale_order_mitxelena/controllers/zip_reports.py
odoo/addons/sale_order_mitxelena/i18n/ca.po
odoo/addons/sale_order_mitxelena/i18n/es.po
odoo/addons/sale_order_mitxelena/i18n/eu.po
odoo/addons/sale_order_mitxelena/i18n/sale_order_mitxelena.pot
odoo/addons/sale_order_mitxelena/models/__init__.py
odoo/addons/sale_order_mitxelena/models/sale_order.py
odoo/addons/sale_order_mitxelena/reports/__init__.py
odoo/addons/sale_order_mitxelena/reports/mitxelena_sale_order_report.py
odoo/addons/sale_order_mitxelena/reports/mitxelena_sale_order_template.xml
odoo/addons/sale_order_mitxelena/reports/mitxelena_standar_layout.xml
odoo/addons/sale_order_mitxelena/reports/sale_order_report_template.xml
odoo/addons/sale_order_mitxelena/security/ir.model.access.csv
odoo/addons/sale_order_mitxelena/static/report/img/AS-9100-bw.tm.jpg
odoo/addons/sale_order_mitxelena/static/report/img/UKAS-AND-ISO-9001-bw.tm.png
odoo/addons/sale_order_mitxelena/static/report/img/logo-mitxelena.png
odoo/addons/sale_order_mitxelena/static/report/img/zerbitzua-euskaraz-zb.png
odoo/addons/sale_order_mitxelena/static/src/js/sale_order_line.js
odoo/addons/sale_order_mitxelena/views/sale_order_line_views.xml
odoo/addons/sale_order_mitxelena/wizard/__init__.py
odoo/addons/sale_order_mitxelena/wizard/sale_order_report_wizard.py
odoo/addons/sale_order_mitxelena/wizard/sale_order_report_wizard_view.xml
odoo14_addon_sale_order_mitxelena-14.0.1.0.7.dist-info/METADATA
odoo14_addon_sale_order_mitxelena-14.0.1.0.7.dist-info/WHEEL
odoo14_addon_sale_order_mitxelena-14.0.1.0.7.dist-info/top_level.txt
odoo14_addon_sale_order_mitxelena-14.0.1.0.7.dist-info/RECORD
